loginUtil/__init__.py
loginUtil/main.py
loginUtil-0.0.7.dist-info/LICENSE
loginUtil-0.0.7.dist-info/METADATA
loginUtil-0.0.7.dist-info/WHEEL
loginUtil-0.0.7.dist-info/top_level.txt
loginUtil-0.0.7.dist-info/RECORD
