Metadata-Version: 2.1
Name: loginUtil
Version: 0.0.7
Summary: login util
Home-page: https://github.com/lucasammer/login-util-stable
Author: lucasammer
Author-email: me@lucasammer.com
License: UNKNOWN
Platform: UNKNOWN
Classifier: Programming Language :: Python :: 3
Classifier: License :: OSI Approved :: MIT License
Classifier: Operating System :: OS Independent
Requires-Python: >=3.6
